Workbook

Sheet Annual salary calculator
B2: 年总包和到手薪资计算 | F2: 变量配置 | J2: 每月缴纳个税金额计算
B3: 项目 | C3: 金额 | D3: 计算方式 | F3: 项目 | G3: 金额 | J3: 月份 | K3: 工资 | L3: 累计应纳税所得额 | M3: 累计应纳税额 | N3: 本月纳税额 | O3: 本月到手 | P3: 每月应纳税所得额扣除
B4: 工资 | C4: =G4*G6+G5 -> 254400 | D4: =TEXT(G4,"0")&" × "&TEXT(G6,"0")&" + "&TEXT(G5,"0") -> 20000 × 12 + 14400 | F4: 月薪 | G4: 20000 | J4: 1 | K4: =$G$4 -> 20000 | L4: =SUM($K$4:$K4)-$P$4*J4 -> 9000 | M4: =MAX(0,L4)*VLOOKUP(MAX(0,L4),Info!$A$1:$C$8,2,TRUE)-VLOOKUP(MAX(0,L4),Info!$A$1:$C$8,3,TRUE) -> 270 | N4: =M4-IF(J4=1,0,M3) -> 270 | O4: =K4-N4-($C$12+$C$16)/12 -> 15230 | P4: =5000+$G$20+($C$12+$C$16)/12 -> 11000
B5: 年终 | C5: =G4*G7 -> 80000 | D5: =TEXT(G4,"0")&" × "&TEXT(3,"0") -> 20000 × 3 | F5: 津贴（年） | G5: 14400 | J5: 2 | K5: =$G$4 -> 20000 | L5: =SUM($K$4:$K5)-$P$4*J5 -> 18000 | M5: =MAX(0,L5)*VLOOKUP(MAX(0,L5),Info!$A$1:$C$8,2,TRUE)-VLOOKUP(MAX(0,L5),Info!$A$1:$C$8,3,TRUE) -> 540 | N5: =M5-IF(J5=1,0,M4) -> 270 | O5: =K5-N5-($C$12+$C$16)/12 -> 15230
B6: 总包 | C6: =C4+C5 -> 334400 | D6: =TEXT(C4,"0")&" + "&TEXT(C5,"0") -> 254400 + 80000 | F6: 工资期数 | G6: 12 | J6: 3 | K6: =K5 -> 20000 | L6: =SUM($K$4:$K6)-$P$4*J6 -> 27000 | M6: =MAX(0,L6)*VLOOKUP(MAX(0,L6),Info!$A$1:$C$8,2,TRUE)-VLOOKUP(MAX(0,L6),Info!$A$1:$C$8,3,TRUE) -> 810 | N6: =M6-IF(J6=1,0,M5) -> 270 | O6: =K6-N6-($C$12+$C$16)/12 -> 15230
F7: 年终期数 | G7: 4 | J7: 4 | K7: =K6 -> 20000 | L7: =SUM($K$4:$K7)-$P$4*J7 -> 36000 | M7: =MAX(0,L7)*VLOOKUP(MAX(0,L7),Info!$A$1:$C$8,2,TRUE)-VLOOKUP(MAX(0,L7),Info!$A$1:$C$8,3,TRUE) -> 1080 | N7: =M7-IF(J7=1,0,M6) -> 270 | O7: =K7-N7-($C$12+$C$16)/12 -> 15230
B8: 应纳税所得额（工资） | C8: =MAX(0,C4-G28-G8-C12-C16) -> 122400 | D8: =TEXT(C4,"0")&" - "&TEXT(G28,"0")&" - "&TEXT(G8,"0")&" - "&TEXT(C12,"0")&" - "&TEXT(C16,"0") -> 254400 - 60000 - 18000 - 25200 - 28800 | F8: 专项扣除 | G8: =G20*12 -> 18000 | J8: 5 | K8: =K7 -> 20000 | L8: =SUM($K$4:$K8)-$P$4*J8 -> 45000 | M8: =MAX(0,L8)*VLOOKUP(MAX(0,L8),Info!$A$1:$C$8,2,TRUE)-VLOOKUP(MAX(0,L8),Info!$A$1:$C$8,3,TRUE) -> 1980 | N8: =M8-IF(J8=1,0,M7) -> 900 | O8: =K8-N8-($C$12+$C$16)/12 -> 14600
B9: 应纳税所得额（年终） | C9: =MAX(0,C5) -> 80000 | D9: =TEXT(C9,"0") -> 80000 | F9: 公积金缴存比例 | G9: 0.12 | J9: 6 | K9: =K8 -> 20000 | L9: =SUM($K$4:$K9)-$P$4*J9 -> 54000 | M9: =MAX(0,L9)*VLOOKUP(MAX(0,L9),Info!$A$1:$C$8,2,TRUE)-VLOOKUP(MAX(0,L9),Info!$A$1:$C$8,3,TRUE) -> 2880 | N9: =M9-IF(J9=1,0,M8) -> 900 | O9: =K9-N9-($C$12+$C$16)/12 -> 14600
B10: 应纳税额（工资） | C10: =C8*VLOOKUP(C8,Info!$A$2:$C$8,2,TRUE)-VLOOKUP(C8,Info!$A$2:$C$8,3,TRUE) -> 9720 | D10: =TEXT(C8,"0")&" × "&TEXT(VLOOKUP(C8,Info!A1:C8,2,TRUE),"0%")&" - "&TEXT(VLOOKUP(C8,Info!A1:C8,3,TRUE),"0") -> 122400 × 10% - 2520 | J10: 7 | K10: =K9 -> 20000 | L10: =SUM($K$4:$K10)-$P$4*J10 -> 63000 | M10: =MAX(0,L10)*VLOOKUP(MAX(0,L10),Info!$A$1:$C$8,2,TRUE)-VLOOKUP(MAX(0,L10),Info!$A$1:$C$8,3,TRUE) -> 3780 | N10: =M10-IF(J10=1,0,M9) -> 900 | O10: =K10-N10-($C$12+$C$16)/12 -> 14600
B11: 应纳税额（年终） | C11: =C5*VLOOKUP(C5,Info!A12:C18,2,TRUE)-VLOOKUP(C5,Info!A12:C18,3,TRUE) -> 7790 | D11: =TEXT(C5,"0")&" × "&TEXT(VLOOKUP(C5,Info!A12:C18,2,TRUE),"0%")&" - "&TEXT(VLOOKUP(C5,Info!A12:C18,3,TRUE),"0") -> 80000 × 10% - 210 | F11: 专项扣除配置 | J11: 8 | K11: =K10 -> 20000 | L11: =SUM($K$4:$K11)-$P$4*J11 -> 72000 | M11: =MAX(0,L11)*VLOOKUP(MAX(0,L11),Info!$A$1:$C$8,2,TRUE)-VLOOKUP(MAX(0,L11),Info!$A$1:$C$8,3,TRUE) -> 4680 | N11: =M11-IF(J11=1,0,M10) -> 900 | O11: =K11-N11-($C$12+$C$16)/12 -> 14600
B12: 每年缴纳五险 | C12: =MEDIAN($G$4,$G$25,$G$24)*$G29*12 -> 25200 | D12: =TEXT(MEDIAN($G$4,$G$25,$G$24),"0")&" × "&TEXT($G29,"0.0%")&" × 12" -> 20000 × 10.5% × 12 | F12: 项目 | G12: 金额（每月） | J12: 9 | K12: =K11 -> 20000 | L12: =SUM($K$4:$K12)-$P$4*J12 -> 81000 | M12: =MAX(0,L12)*VLOOKUP(MAX(0,L12),Info!$A$1:$C$8,2,TRUE)-VLOOKUP(MAX(0,L12),Info!$A$1:$C$8,3,TRUE) -> 5580 | N12: =M12-IF(J12=1,0,M11) -> 900 | O12: =K12-N12-($C$12+$C$16)/12 -> 14600
B13: 每年缴纳养老保险 | C13: =MEDIAN($G$4,$G$25,$G$24)*$G30*12 -> 19200 | D13: =TEXT(MEDIAN($G$4,$G$25,$G$24),"0")&" × "&TEXT($G30,"0.0%")&" × 12" -> 20000 × 8.0% × 12 | F13: 子女教育扣除 | G13: 不符合，扣除0元 | H13: =VLOOKUP(G13,Info!A29:B33,2,) -> 0 | J13: 10 | K13: =K12 -> 20000 | L13: =SUM($K$4:$K13)-$P$4*J13 -> 90000 | M13: =MAX(0,L13)*VLOOKUP(MAX(0,L13),Info!$A$1:$C$8,2,TRUE)-VLOOKUP(MAX(0,L13),Info!$A$1:$C$8,3,TRUE) -> 6480 | N13: =M13-IF(J13=1,0,M12) -> 900 | O13: =K13-N13-($C$12+$C$16)/12 -> 14600
B14: 每年缴纳医疗保险 | C14: =MEDIAN($G$4,$G$25,$G$24)*$G31*12 -> 4800 | D14: =TEXT(MEDIAN($G$4,$G$25,$G$24),"0")&" × "&TEXT($G31,"0.0%")&" × 12" -> 20000 × 2.0% × 12 | F14: 继续教育扣除 | G14: 不符合，扣除0元 | H14: =VLOOKUP(G14,Info!C29:D30,2,) -> 0 | J14: 11 | K14: =K13 -> 20000 | L14: =SUM($K$4:$K14)-$P$4*J14 -> 99000 | M14: =MAX(0,L14)*VLOOKUP(MAX(0,L14),Info!$A$1:$C$8,2,TRUE)-VLOOKUP(MAX(0,L14),Info!$A$1:$C$8,3,TRUE) -> 7380 | N14: =M14-IF(J14=1,0,M13) -> 900 | O14: =K14-N14-($C$12+$C$16)/12 -> 14600
B15: 每年缴纳失业保险 | C15: =MEDIAN($G$4,$G$25,$G$24)*$G32*12 -> 1200 | D15: =TEXT(MEDIAN($G$4,$G$25,$G$24),"0")&" × "&TEXT($G32,"0.0%")&" × 12" -> 20000 × 0.5% × 12 | F15: 赡养老人扣除 | G15: 不符合，扣除0元 | H15: =VLOOKUP(G15,Info!E29:F32,2,) -> 0 | J15: 12 | K15: =K14 -> 20000 | L15: =SUM($K$4:$K15)-$P$4*J15 -> 108000 | M15: =MAX(0,L15)*VLOOKUP(MAX(0,L15),Info!$A$1:$C$8,2,TRUE)-VLOOKUP(MAX(0,L15),Info!$A$1:$C$8,3,TRUE) -> 8280 | N15: =M15-IF(J15=1,0,M14) -> 900 | O15: =K15-N15-($C$12+$C$16)/12 -> 14600
B16: 每年缴纳公积金 | C16: =MEDIAN(G4,G27,G26)*G9*12 -> 28800 | D16: =TEXT(MEDIAN(G4,2490,40694),"0")&" × 12% × 12" -> 20000 × 12% × 12 | F16: 住房贷款利息扣除 | G16: 不符合，扣除0元 | H16: =VLOOKUP(G16,Info!G29:H31,2,) -> 0
F17: 住房租金扣除 | G17: 直辖市、省会城市、计划单列市等，扣除1500元 | H17: =VLOOKUP(G17,Info!I29:J32,2,) -> 1500
B18: 到手（含公积金） | C18: =C6-C13-C15+C16-C10-C11+C14 -> 330090 | D18: =TEXT(C6,"0")&" - "&TEXT(C12,"0")&" + "&TEXT(C16,"0")&" - "&TEXT(C10,"0")&" - "&TEXT(C11,"0") -> 334400 - 25200 + 28800 - 9720 - 7790 | F18: 3岁以下婴幼儿照护 | G18: 不符合，扣除0元 | H18: =VLOOKUP(G18,Info!K29:L31,2,) -> 0
F19: 个人养老金 | G19: 0
F20: 共计（年） | G20: =SUM(H13:H18) -> 1500
C22: =C10+C11+C13+C15-C14-C16 -> 4310 | F22: 五险一金配置
F23: 常量 | G23: 金额
F24: 社保缴费基数上限 | G24: 25300
F25: 社保缴费基数下限 | G25: 4986
F26: 公积金缴存基数上限 | G26: 40694
F27: 公积金缴存基数下限 | G27: 2490
F28: 免征额 | G28: 60000
F29: 社保缴费比例 | G29: 0.105
F30: 养老保险个人缴纳比例 | G30: 0.08
F31: 医疗保险个人缴纳比例 | G31: 0.02
F32: 失业保险个人缴纳比例 | G32: 0.005

Sheet Info
A1: 全年应纳税所得额 | B1: 税率（%） | C1: 速算扣除数
A2: 0 | B2: 0.03 | C2: 0
A3: 36000 | B3: 0.1 | C3: 2520
A4: 144000 | B4: 0.2 | C4: 16920
A5: 300000 | B5: 0.25 | C5: 31920
A6: 420000 | B6: 0.3 | C6: 52920
A7: 660000 | B7: 0.35 | C7: 85920
A8: 960000 | B8: 0.45 | C8: 181920
A11: 全年应纳税所得额 | B11: 税率（%） | C11: 速算扣除数
A12: 0 | B12: 0.03 | C12: 0
A13: 36000 | B13: 0.1 | C13: 210
A14: 144000 | B14: 0.2 | C14: 1410
A15: 300000 | B15: 0.25 | C15: 2660
A16: 420000 | B16: 0.3 | C16: 4410
A17: 660000 | B17: 0.35 | C17: 7160
A18: 960000 | B18: 0.45 | C18: 15160
B21: 北京 | C21: 上海 | D21: 广州 | E21: 深圳 | F21: 杭州
A22: 社保缴纳基数上限 | B22: 35811 | C22: 37302 | D22: 27549 | E22: 27549 | F22: 25299
A23: 社保缴纳基数下限 | B23: 7162 | C23: 7460 | D23: 5510 | E23: 4775 | F23: 4986
A24: 公积金缴存基数上限 | B24: 35811 | C24: 37302 | D24: 39828 | E24: 44265 | F24: 40694
A25: 公积金缴存基数下限 | B25: 2540 | C25: 2690 | D25: 2500 | E25: 2360 | F25: 2490
A28: 子女教育扣除 | B28: 金额 | C28: 继续教育扣除 | D28: 金额 | E28: 赡养老人扣除 | F28: 金额 | G28: 住房贷款利息扣除 | H28: 金额 | I28: 住房租金扣除 | J28: 金额 | K28: 3岁以下婴幼儿照护 | L28: 金额
A29: 不符合，扣除0元 | B29: 0 | C29: 不符合，扣除0元 | D29: 0 | E29: 不符合，扣除0元 | F29: 0 | G29: 不符合，扣除0元 | H29: 0 | I29: 不符合，扣除0元 | J29: 0 | K29: 不符合，扣除0元 | L29: 0
A30: 一个孩子，夫妻各扣除1000元 | B30: 1000 | C30: 接受学历教育中，扣除400 | D30: 400 | E30: 独生子女，扣除3000元 | F30: 3000 | G30: 夫妻各扣除500元 | H30: 500 | I30: 所在城市户籍人口少于100万，扣除800元 | J30: 800 | K30: 一方扣除2000元 | L30: 2000
A31: 一个孩子，仅有一方扣除2000元 | B31: 2000 | E31: 两兄弟姐妹分摊，扣除1500元 | F31: 1500 | G31: 仅由一方扣除1000元 | H31: 1000 | I31: 所在城市户籍人口超过100万，扣除1100元 | J31: 1100 | K31: 夫妻各扣除1000元 | L31: 1000
A32: 两个孩子，夫妻各扣除2000元 | B32: 2000 | E32: 三兄弟姐妹分摊，扣除1000元 | F32: 1000 | I32: 直辖市、省会城市、计划单列市等，扣除1500元 | J32: 1500
A33: 两个孩子，仅有一方扣除4000元 | B33: 4000
